NorconsultPiPythonDevelop/copyFiles.py
NorconsultPiPythonDevelop/init.py
NorconsultPiPythonDevelop/serverPaths.py
norconsultpipythondevelop-1.2.2.dist-info/licenses/LICENSE.txt
norconsultpipythondevelop-1.2.2.dist-info/METADATA
norconsultpipythondevelop-1.2.2.dist-info/WHEEL
norconsultpipythondevelop-1.2.2.dist-info/top_level.txt
norconsultpipythondevelop-1.2.2.dist-info/RECORD
