Metadata-Version: 2.4
Name: norconsultpipythondevelop
Version: 1.2.2
Summary: Python Wrapper for PAM-Integrated API (Develop)
Home-page: 
Author: Norconsult
Author-email: havard.anfinsen@norconsult.com
Classifier: Programming Language :: Python :: 3
Classifier: Operating System :: Microsoft :: Windows
License-File: LICENSE.txt
Requires-Dist: pythonnet>=3.0.1
Requires-Dist: msal>=1.1.0
Requires-Dist: requests>=2.25.0
Dynamic: author
Dynamic: author-email
Dynamic: classifier
Dynamic: description-content-type
Dynamic: license-file
Dynamic: requires-dist
Dynamic: summary
